__both__/__init__.py
__both__/py2/__init__.py
__both__/py3/__init__.py
__transform__/__init__.py
both/__init__.py
both/fixes/__init__.py
both/fixes/fix_dict.py
both/transforms/__init__.py
both-0.1.1.dist-info/LICENSE
both-0.1.1.dist-info/METADATA
both-0.1.1.dist-info/WHEEL
both-0.1.1.dist-info/top_level.txt
both-0.1.1.dist-info/RECORD
