Metadata-Version: 2.1
Name: both
Version: 0.1.1
Summary: Python compatibility layer
Home-page: https://bakkerthehacker.github.io/both/
Author: Grant Bakker
Author-email: grant@bakker.pw
License: UNKNOWN
Platform: UNKNOWN
Classifier: Programming Language :: Python :: 2.7
Classifier: Programming Language :: Python :: 3
Classifier: Operating System :: OS Independent
Classifier: License :: OSI Approved :: MIT License
Requires-Dist: six
Requires-Dist: source-transform (>=0.1.2)
Requires-Dist: future
